[
  {
    "actual_combo": 0,
    "combo_stats": {
      "damage": 5025,
      "drive_used": 38000,
      "hit_type": "PC",
      "super_used": 10000
    },
    "counter_type": 2,
    "damage_at_step": 1080,
    "delay_from_prev": 0,
    "dual_threshold": false,
    "expected_combo": 1,
    "expected_hp": 1800,
    "facing_left": false,
    "group_id": 1,
    "has_hit": true,
    "hold_frames": 0,
    "hold_partial_check": false,
    "id": 977,
    "is_holdable": false,
    "is_projectile_hit": false,
    "motion": "214+HP",
    "recorded_by": 0,
    "start_pos_p1": 6.66575439453125,
    "start_pos_p1_raw": 43684688,
    "start_pos_p2": 7.65,
    "start_pos_p2_raw": 50135040,
    "timeline": [
      "1f : 4",
      "2f : 1",
      "3f : 2",
      "4f : 3",
      "4f : 6+HP",
      "4f : 9+HP",
      "2f : 8+HP",
      "43f : 5+HP",
      "2f : 5",
      "7f : 1",
      "6f : 1+HP",
      "1f : 2+HP",
      "2f : 2",
      "2f : 3",
      "5f : 6",
      "1f : 6+MP+HP",
      "14f : 9+MP+HP",
      "1f : 9",
      "1f : 8",
      "1f : 5",
      "7f : 4",
      "4f : 4+HP",
      "5f : 4",
      "4f : 4+HP",
      "4f : 4",
      "5f : 4+HP",
      "5f : 4",
      "29f : 5",
      "12f : 6",
      "3f : 6+HK",
      "5f : 6",
      "7f : 6+HK",
      "3f : 6",
      "3f : 3",
      "2f : 2",
      "3f : 1",
      "4f : 4",
      "4f : 4+MP+HP",
      "40f : 5+MP+HP",
      "2f : 5",
      "4f : 6",
      "2f : 3",
      "2f : 2",
      "2f : 1",
      "2f : 4",
      "2f : 7",
      "2f : 8",
      "1f : 9",
      "1f : 6",
      "1f : 3",
      "1f : 2",
      "3f : 1",
      "1f : 4",
      "4f : 4+MK",
      "2f : 5+MK",
      "29f : 5",
      "9f : 5+LP",
      "51f : 5",
      "4f : 4",
      "2f : 1",
      "3f : 2",
      "2f : 3",
      "3f : 6",
      "13f : 6+HK",
      "6f : 5+HK",
      "8f : 5",
      "5f : 2",
      "149f : 5"
    ],
    "_xt_meta": {
      "schema": "xt.combo_trial.meta.v1",
      "character": "Akuma",
      "title": "版边一气最大伤害连段",
      "author": "泽",
      "note": "",
      "version": 1
    }
  },
  {
    "actual_combo": 0,
    "counter_type": 0,
    "damage_at_step": 1980,
    "delay_from_prev": 63,
    "dual_threshold": false,
    "expected_combo": 2,
    "expected_hp": 1800,
    "facing_left": false,
    "group_id": 2,
    "has_hit": true,
    "hold_frames": 0,
    "hold_partial_check": false,
    "id": 630,
    "is_holdable": false,
    "is_projectile_hit": false,
    "motion": "2HP"
  },
  {
    "actual_combo": 0,
    "counter_type": 0,
    "damage_at_step": 2540,
    "delay_from_prev": 21,
    "dual_threshold": false,
    "expected_combo": 3,
    "expected_hp": 1800,
    "facing_left": false,
    "group_id": 3,
    "has_hit": true,
    "hold_frames": 0,
    "hold_partial_check": false,
    "id": 978,
    "is_holdable": false,
    "is_projectile_hit": false,
    "motion": "214+PP"
  },
  {
    "actual_combo": 0,
    "counter_type": 0,
    "damage_at_step": 3030,
    "delay_from_prev": 33,
    "dual_threshold": false,
    "expected_combo": 5,
    "expected_hp": 1800,
    "facing_left": false,
    "group_id": 3,
    "has_hit": true,
    "hold_frames": 0,
    "hold_partial_check": true,
    "id": 986,
    "is_holdable": false,
    "is_projectile_hit": false,
    "motion": ">6+P"
  },
  {
    "actual_combo": 0,
    "counter_type": 0,
    "damage_at_step": 3510,
    "delay_from_prev": 64,
    "dual_threshold": false,
    "expected_combo": 6,
    "expected_hp": 1800,
    "facing_left": false,
    "group_id": 4,
    "has_hit": true,
    "hold_frames": 0,
    "hold_partial_check": false,
    "id": 672,
    "is_holdable": false,
    "is_projectile_hit": false,
    "motion": "4HK"
  },
  {
    "actual_combo": 0,
    "charge_max": 24,
    "charge_min": 24,
    "charge_status": "Maxed",
    "counter_type": 0,
    "damage_at_step": 4185,
    "delay_from_prev": 25,
    "dual_threshold": false,
    "expected_combo": 10,
    "expected_hp": 1800,
    "facing_left": false,
    "group_id": 5,
    "has_hit": true,
    "hold_frames": 29,
    "hold_partial_check": true,
    "id": 904,
    "is_holdable": true,
    "is_projectile_hit": true,
    "motion": "236+PP (OD)",
    "next_auto_id": 914
  },
  {
    "actual_combo": 0,
    "counter_type": 0,
    "damage_at_step": 4185,
    "delay_from_prev": 57,
    "dual_threshold": false,
    "expected_combo": 10,
    "expected_hp": 1800,
    "facing_left": false,
    "group_id": 6,
    "has_hit": true,
    "hold_frames": 0,
    "hold_partial_check": false,
    "id": 37,
    "is_holdable": false,
    "motion": "9"
  },
  {
    "actual_combo": 0,
    "counter_type": 0,
    "damage_at_step": 4785,
    "delay_from_prev": 8,
    "dual_threshold": false,
    "expected_combo": 15,
    "expected_hp": 1800,
    "facing_left": false,
    "group_id": 7,
    "has_hit": true,
    "hold_frames": 0,
    "hold_partial_check": false,
    "id": 1207,
    "is_holdable": false,
    "is_projectile_hit": true,
    "motion": "j.236236+K"
  },
  {
    "actual_combo": 0,
    "counter_type": 0,
    "damage_at_step": 5025,
    "delay_from_prev": 113,
    "dual_threshold": false,
    "expected_combo": 19,
    "expected_hp": 1800,
    "facing_left": false,
    "group_id": 8,
    "has_hit": true,
    "hold_frames": 0,
    "hold_partial_check": false,
    "id": 1022,
    "is_holdable": false,
    "is_projectile_hit": false,
    "motion": "214+HK"
  }
]
